omicslearn/__init__.py
omicslearn/_version.py
omicslearn-0.0.0.dist-info/METADATA
omicslearn-0.0.0.dist-info/WHEEL
omicslearn-0.0.0.dist-info/licenses/LICENSE
omicslearn-0.0.0.dist-info/RECORD
